nvidia_audio2face_3d/__init__.py
nvidia_audio2face_3d/a2x_export_config_pb2.py
nvidia_audio2face_3d/a2x_export_config_pb2.pyi
nvidia_audio2face_3d/a2x_export_config_pb2_grpc.py
nvidia_audio2face_3d/audio2face_pb2.py
nvidia_audio2face_3d/audio2face_pb2.pyi
nvidia_audio2face_3d/audio2face_pb2_grpc.py
nvidia_audio2face_3d/messages_pb2.py
nvidia_audio2face_3d/messages_pb2.pyi
nvidia_audio2face_3d/messages_pb2_grpc.py
nvidia_audio2face_3d/py.typed
nvidia_audio2face_3d-1.3.0.dist-info/METADATA
nvidia_audio2face_3d-1.3.0.dist-info/WHEEL
nvidia_audio2face_3d-1.3.0.dist-info/licenses/LICENSE
nvidia_audio2face_3d-1.3.0.dist-info/RECORD
