Metadata-Version: 2.4
Name: nvidia-audio2face-3d
Version: 1.3.0
Summary: Audio2Face 3D NIM gRPC protoypes and services.
Project-URL: Homepage, https://developer.nvidia.com/ace
Project-URL: Documentation, https://docs.nvidia.com/ace/audio2face-3d-microservice/1.3/index.html
Author-email: NVIDIA ACE <ace-dev@exchange.nvidia.com>
License-Expression: Apache-2.0
License-File: LICENSE
Requires-Python: >=3.8
Requires-Dist: nvidia-ace~=1.0
